pycircleci_async/__init__.py
pycircleci_async/client.py
pycircleci_async/http.py
pycircleci_async-0.1.1.dist-info/LICENSE
pycircleci_async-0.1.1.dist-info/WHEEL
pycircleci_async-0.1.1.dist-info/METADATA
pycircleci_async-0.1.1.dist-info/RECORD
